LICENSE
README.md
pyproject.toml
setup.py
./setup.py
damebasics/__init__.py
damebasics/runtests.sh
damebasics.egg-info/PKG-INFO
damebasics.egg-info/SOURCES.txt
damebasics.egg-info/dependency_links.txt
damebasics.egg-info/entry_points.txt
damebasics.egg-info/not-zip-safe
damebasics.egg-info/requires.txt
damebasics.egg-info/top_level.txt
damebasics/files/__init__.py
damebasics/files/pg1513.txt
damebasics/files/tmp.txt
damebasics/files/tmp2.txt
damebasics/src/__init__.py
damebasics/src/calculator.py
damebasics/src/damebasics.py
damebasics/src/factorial.py
damebasics/src/fib.py
damebasics/src/fraction.py
damebasics/src/hanoi.py
damebasics/src/primes.py
damebasics/src/queuelist.py
damebasics/tests/__init__.py
damebasics/tests/test_arithmetics.py
damebasics/tests/test_collections.py
damebasics/tests/test_control_structures.py
damebasics/tests/test_date.py
damebasics/tests/test_dict.py
damebasics/tests/test_files.py
damebasics/tests/test_lists.py
damebasics/tests/test_network.py
damebasics/tests/test_poo.py
damebasics/tests/test_set.py
damebasics/tests/test_strings.py
damebasics/tests/test_tuples.py