Metadata-Version: 2.1
Name: damebasics
Version: 0.1.9.post1
Summary: Learning basic control structures and basic datastructures from Tests by David Arroyo Menéndez'
Home-page: http://github.com/davidam/damebasics
Author: David Arroyo Menéndez
Author-email: David Arroyo Menéndez <davidam@gmail.com>
Maintainer-email: David Arroyo Menéndez <davidam@gmail.com>
License:                     GNU GENERAL PUBLIC LICENSE
Project-URL: Homepage, https://github.com/davidam/damebasics
Project-URL: Bug Reports, https://github.com/davidam/damebasics/issues
Project-URL: Funding, https://www.paypal.com/donate/?cmd=_donations&business=davidam%40gmail.com&currency_code=EUR&amount=10&source=url
Project-URL: Say Thanks!, https://github.com/davidam/damebasics/wiki
Project-URL: Source, https://github.com/davidam/damebasics/
Keywords: sample,basics,control structures,datastructures,development
Classifier: Development Status :: 3 - Alpha
Classifier: Intended Audience :: Developers
Classifier: Topic :: Software Development :: Build Tools
Classifier: License :: OSI Approved :: GNU General Public License v3 (GPLv3)
Classifier: Programming Language :: Python :: 3
Classifier: Programming Language :: Python :: 3.7
Classifier: Programming Language :: Python :: 3.8
Classifier: Programming Language :: Python :: 3.9
Classifier: Programming Language :: Python :: 3.10
Classifier: Programming Language :: Python :: 3.11
Classifier: Programming Language :: Python :: 3 :: Only
Requires-Python: >=3.7
License-File: LICENSE
Requires-Dist: markdown
Provides-Extra: dev
Requires-Dist: check-manifest; extra == "dev"
Provides-Extra: test
Requires-Dist: coverage; extra == "test"
